<?xml version="1.0" encoding="UTF-8"?>
<prefab name="_Compo_Cabin(Sudo)">
  <size x="46" y="26" z="55"/>
  <blocks>
    <block id="689" name="adobeWhitePole" count="3"/>
    <block id="0" name="air" count="36071"/>
    <block id="827" name="asphaltShingleCNRInside" count="28"/>
    <block id="983" name="asphaltShinglesCNRFull" count="4"/>
    <block id="1467" name="bed02" count="2"/>
    <block id="360" name="boardedWindowsSheet4" count="2"/>
    <block id="949" name="brickPaversBlock" count="322"/>
    <block id="1071" name="brickPaversStairs25" count="3"/>
    <block id="710" name="cabinetFillerBlock" count="27"/>
    <block id="712" name="cabinetTopPlate" count="107"/>
    <block id="1001" name="cabinFlagstoneRamp" count="495"/>
    <block id="309" name="campfire" count="7"/>
    <block id="1120" name="carpet3DrywallBlock" count="1476"/>
    <block id="319" name="ceilingLight01" count="7"/>
    <block id="321" name="ceilingLight02Brass" count="1"/>
    <block id="324" name="ceilingLight05Brass" count="22"/>
    <block id="326" name="ceilingLight07" count="2"/>
    <block id="931" name="chaulkboardPlate" count="13"/>
    <block id="542" name="cntBirdnest" count="1"/>
    <block id="737" name="cntBookcase" count="2"/>
    <block id="838" name="cntCabinet" count="23"/>
    <block id="944" name="cntCabinetOldSink" count="1"/>
    <block id="1077" name="cntCabinetTop" count="12"/>
    <block id="892" name="cntCardboardBox" count="10"/>
    <block id="519" name="cntDesk01" count="5"/>
    <block id="520" name="cntDesk02" count="1"/>
    <block id="841" name="cntFridgeBottom" count="32"/>
    <block id="840" name="cntFridgeTop" count="8"/>
    <block id="629" name="cntGraniteSink" count="5"/>
    <block id="626" name="cntLockers" count="12"/>
    <block id="286" name="cntMedicineCabinet" count="2"/>
    <block id="557" name="cntMunitionsBox" count="1"/>
    <block id="337" name="cntNightstand" count="9"/>
    <block id="435" name="cntToilet02" count="2"/>
    <block id="335" name="cntTrash_can01" count="2"/>
    <block id="342" name="cntTrashPile03" count="1"/>
    <block id="346" name="cntTrashPile07" count="2"/>
    <block id="347" name="cntTrashPile08" count="2"/>
    <block id="1076" name="cntWallOven" count="2"/>
    <block id="367" name="cntWallSafe" count="3"/>
    <block id="836" name="cobblestoneStairs25" count="4"/>
    <block id="1164" name="commercialDoor1_v1" count="1"/>
    <block id="1169" name="commercialDoor2_v3" count="1"/>
    <block id="1174" name="commercialDoor4_v2" count="1"/>
    <block id="783" name="concretePlate" count="6"/>
    <block id="1072" name="concreteStairs25" count="6"/>
    <block id="926" name="corrugatedMetalSheetDuplicate" count="3"/>
    <block id="1052" name="dotsAsphaltShinglesCNRInside" count="4"/>
    <block id="468" name="driftwood" count="5"/>
    <block id="822" name="dropCeilingRedWoodTrimBlock" count="763"/>
    <block id="1115" name="drywallBlock" count="125"/>
    <block id="971" name="drywallCeilingRamp" count="22"/>
    <block id="881" name="DrywallIndustrialTileBlock" count="22"/>
    <block id="547" name="endTable" count="4"/>
    <block id="548" name="endTableLamp" count="4"/>
    <block id="621" name="faucetBrass02" count="3"/>
    <block id="622" name="faucetBrass04" count="1"/>
    <block id="1102" name="fenceWoodSheet" count="31"/>
    <block id="948" name="flagstoneBlock" count="1371"/>
    <block id="950" name="flagstoneDrywallBaseboardBlock" count="2"/>
    <block id="945" name="flagstoneDrywallBlock" count="1"/>
    <block id="970" name="flagstoneShinglesRamp" count="973"/>
    <block id="556" name="forge" count="6"/>
    <block id="627" name="fountain" count="2"/>
    <block id="1160" name="glassBusinessBlock" count="264"/>
    <block id="395" name="glassIndustrialCTRPlate" count="27"/>
    <block id="2" name="grass" count="64"/>
    <block id="16" name="gravel" count="385"/>
    <block id="1176" name="houseFrontDoor1_v1" count="6"/>
    <block id="1227" name="houseFrontDoor2_v2" count="3"/>
    <block id="432" name="mineHubcap" count="1"/>
    <block id="521" name="officeChair01" count="2"/>
    <block id="277" name="painting01" count="2"/>
    <block id="907" name="painting02" count="3"/>
    <block id="1099" name="panelingBurntPlate" count="3"/>
    <block id="1116" name="peachDrywallBaseboardBlock" count="334"/>
    <block id="764" name="plantedGoldenrod3Harvest" count="26"/>
    <block id="853" name="plantedYucca3Harvest" count="2"/>
    <block id="316" name="porchLight01" count="2"/>
    <block id="317" name="porchLight04" count="12"/>
    <block id="1145" name="railingWroughtIronSheet" count="37"/>
    <block id="204" name="rConcreteBlock" count="4981"/>
    <block id="952" name="redWoodBlock" count="146"/>
    <block id="953" name="redWoodFloorBlock" count="45"/>
    <block id="835" name="redWoodStairs25" count="18"/>
    <block id="298" name="rock02" count="1"/>
    <block id="300" name="rock04" count="1"/>
    <block id="837" name="rug01Block" count="154"/>
    <block id="1118" name="rug01DrywallBlock" count="29"/>
    <block id="549" name="sectionalArm2" count="11"/>
    <block id="550" name="sectionalCorner2" count="8"/>
    <block id="551" name="sectionalMiddle2" count="58"/>
    <block id="1106" name="shutters1Plate" count="7"/>
    <block id="1" name="stone" count="15416"/>
    <block id="522" name="storeShelving01" count="21"/>
    <block id="524" name="storeShelving01Top" count="12"/>
    <block id="867" name="tanDrywallRamp" count="7"/>
    <block id="28" name="terrainFiller" count="1083"/>
    <block id="279" name="tile3Stairs50" count="4"/>
    <block id="278" name="tileFloor3Block" count="17"/>
    <block id="724" name="tileFloor3Stairs25" count="1"/>
    <block id="908" name="tileFloor4Block" count="366"/>
    <block id="1073" name="tileFloor4Stairs25" count="11"/>
    <block id="885" name="treePlant02" count="25"/>
    <block id="552" name="tv" count="3"/>
    <block id="554" name="tv_large_1" count="3"/>
    <block id="555" name="tv_large_2" count="3"/>
    <block id="1093" name="ventDuctBlock" count="48"/>
    <block id="930" name="ventDuctRamp" count="6"/>
    <block id="325" name="wallLight01" count="4"/>
    <block id="824" name="waterStaticBucket" count="6"/>
    <block id="1203" name="window03Broke4" count="3"/>
    <block id="1192" name="woodBarricadePlate" count="1"/>
    <block id="990" name="woodPainted3Pole" count="4"/>
    <block id="164" name="woodPlate" count="3"/>
    <block id="988" name="woodPole" count="10"/>
  </blocks>
</prefab>
