<?xml version="1.0" encoding="UTF-8"?>
<prefab name="business_red_brick_02">
  <size x="16" y="15" z="30"/>
  <blocks>
    <block id="0" name="air" count="5195"/>
    <block id="365" name="airConditioner" count="1"/>
    <block id="978" name="asphaltBlock" count="204"/>
    <block id="997" name="awningGreenBlock" count="12"/>
    <block id="995" name="awningGreenRamp" count="33"/>
    <block id="360" name="boardedWindowsSheet4" count="4"/>
    <block id="954" name="brickDecayedBlock" count="668"/>
    <block id="583" name="brickDecayedBroke1Block" count="17"/>
    <block id="584" name="brickDecayedBroke2Block" count="3"/>
    <block id="585" name="brickDecayedBroke3Block" count="3"/>
    <block id="1041" name="brickDecayedRamp" count="1"/>
    <block id="709" name="cabinetOldFillerBlock" count="7"/>
    <block id="321" name="ceilingLight02Brass" count="5"/>
    <block id="518" name="chair01" count="1"/>
    <block id="1261" name="cntBeerCooler" count="2"/>
    <block id="542" name="cntBirdnest" count="1"/>
    <block id="737" name="cntBookcase" count="1"/>
    <block id="1456" name="cntCar03Red" count="1"/>
    <block id="1340" name="cntCashRegister" count="1"/>
    <block id="361" name="cntCorpseLoot01" count="1"/>
    <block id="520" name="cntDesk02" count="1"/>
    <block id="623" name="cntFileCabinet" count="2"/>
    <block id="628" name="cntGunSafe" count="1"/>
    <block id="369" name="cntMailBox01" count="1"/>
    <block id="335" name="cntTrash_can01" count="1"/>
    <block id="347" name="cntTrashPile08" count="1"/>
    <block id="1164" name="commercialDoor1_v1" count="1"/>
    <block id="1166" name="commercialDoor1_v3" count="1"/>
    <block id="211" name="concreteBlock" count="8"/>
    <block id="775" name="concreteHalf" count="42"/>
    <block id="1072" name="concreteStairs25" count="2"/>
    <block id="926" name="corrugatedMetalSheetDuplicate" count="6"/>
    <block id="1215" name="doorFrameMetal1" count="1"/>
    <block id="1216" name="doorFrameMetal2" count="1"/>
    <block id="1219" name="doorFrameMetalBoarded1" count="1"/>
    <block id="1220" name="doorFrameMetalBoarded2" count="1"/>
    <block id="1482" name="garbage_decor1" count="1"/>
    <block id="1483" name="garbage_decor2" count="1"/>
    <block id="1484" name="garbage_decor3" count="1"/>
    <block id="16" name="gravel" count="84"/>
    <block id="558" name="ironBars" count="2"/>
    <block id="389" name="ladderMetal" count="7"/>
    <block id="883" name="lootGarage" count="1"/>
    <block id="874" name="lootHouse" count="3"/>
    <block id="466" name="mattressFlat" count="1"/>
    <block id="312" name="oldChair" count="2"/>
    <block id="1195" name="plainWoodBarricade02CTRPlate" count="6"/>
    <block id="1108" name="plywoodOsbCTRPlate" count="3"/>
    <block id="318" name="porchLight04Brass" count="3"/>
    <block id="723" name="railingBlackSheet" count="4"/>
    <block id="1144" name="railingOldWoodSheet" count="6"/>
    <block id="1348" name="shoppingBasketEmpty" count="1"/>
    <block id="1326" name="signShopColdBeer" count="2"/>
    <block id="1927" name="signShopOpen" count="1"/>
    <block id="522" name="storeShelving01" count="11"/>
    <block id="524" name="storeShelving01Top" count="21"/>
    <block id="525" name="storeShelving01TopDouble" count="8"/>
    <block id="28" name="terrainFiller" count="396"/>
    <block id="1090" name="tileFloor1WoodPainted2Block" count="315"/>
    <block id="578" name="treeBurntPine02" count="1"/>
    <block id="871" name="treeDeadPineLeaf" count="4"/>
    <block id="569" name="treeDeadShrub" count="1"/>
    <block id="1093" name="ventDuctBlock" count="11"/>
    <block id="930" name="ventDuctRamp" count="1"/>
    <block id="618" name="whiteSidingWoodPanelBurnt7" count="1"/>
    <block id="656" name="window02" count="11"/>
    <block id="1196" name="window02Broken01CTRPlate" count="6"/>
    <block id="1197" name="window02Broken02CTRPlate" count="11"/>
    <block id="1199" name="window02Broken03CTRPlate" count="14"/>
    <block id="1193" name="woodBarricadeCTRPlate" count="3"/>
    <block id="220" name="woodBlock" count="8"/>
    <block id="988" name="woodPole" count="4"/>
    <block id="237" name="woodStairs25" count="12"/>
  </blocks>
</prefab>
