<?xml version="1.0" encoding="UTF-8"?>
<prefab name="business_red_brick_06">
  <size x="27" y="8" z="30"/>
  <blocks>
    <block id="0" name="air" count="4163"/>
    <block id="365" name="airConditioner" count="1"/>
    <block id="978" name="asphaltBlock" count="336"/>
    <block id="360" name="boardedWindowsSheet4" count="5"/>
    <block id="210" name="brickBlock" count="367"/>
    <block id="1339" name="cashRegisterEmpty" count="1"/>
    <block id="320" name="ceilingLight02" count="2"/>
    <block id="1261" name="cntBeerCooler" count="2"/>
    <block id="542" name="cntBirdnest" count="1"/>
    <block id="737" name="cntBookcase" count="1"/>
    <block id="1074" name="cntCabinetOldBottom" count="1"/>
    <block id="944" name="cntCabinetOldSink" count="1"/>
    <block id="1458" name="cntCar03Yellow" count="1"/>
    <block id="892" name="cntCardboardBox" count="2"/>
    <block id="368" name="cntCorpseLoot02" count="1"/>
    <block id="1481" name="cntDumpster" count="1"/>
    <block id="623" name="cntFileCabinet" count="1"/>
    <block id="371" name="cntMailBox03" count="1"/>
    <block id="1347" name="cntShoppingCart" count="1"/>
    <block id="427" name="cntSportsBag01" count="1"/>
    <block id="335" name="cntTrash_can01" count="1"/>
    <block id="340" name="cntTrashPile01" count="1"/>
    <block id="343" name="cntTrashPile04" count="3"/>
    <block id="348" name="cntTrashPile09" count="2"/>
    <block id="367" name="cntWallSafe" count="1"/>
    <block id="1164" name="commercialDoor1_v1" count="2"/>
    <block id="211" name="concreteBlock" count="88"/>
    <block id="779" name="concreteBricksBlock" count="76"/>
    <block id="377" name="concretePillar100" count="12"/>
    <block id="1072" name="concreteStairs25" count="5"/>
    <block id="393" name="concreteTrimRamp" count="23"/>
    <block id="926" name="corrugatedMetalSheetDuplicate" count="3"/>
    <block id="1009" name="curtain_bottom1Sheet3" count="1"/>
    <block id="799" name="curtain_top1Sheet3" count="1"/>
    <block id="1219" name="doorFrameMetalBoarded1" count="1"/>
    <block id="1220" name="doorFrameMetalBoarded2" count="1"/>
    <block id="619" name="faucet02" count="1"/>
    <block id="1482" name="garbage_decor1" count="1"/>
    <block id="1483" name="garbage_decor2" count="1"/>
    <block id="16" name="gravel" count="84"/>
    <block id="1262" name="greenMetalRamp" count="3"/>
    <block id="558" name="ironBars" count="4"/>
    <block id="788" name="ladderWood" count="5"/>
    <block id="874" name="lootHouse" count="2"/>
    <block id="1210" name="miniblindBottomSheet" count="2"/>
    <block id="1209" name="miniblindTopSheet" count="2"/>
    <block id="521" name="officeChair01" count="2"/>
    <block id="1195" name="plainWoodBarricade02CTRPlate" count="2"/>
    <block id="1108" name="plywoodOsbCTRPlate" count="1"/>
    <block id="317" name="porchLight04" count="1"/>
    <block id="1420" name="rustyIronTable" count="3"/>
    <block id="1326" name="signShopColdBeer" count="1"/>
    <block id="1927" name="signShopOpen" count="1"/>
    <block id="522" name="storeShelving01" count="23"/>
    <block id="523" name="storeShelving01Double" count="32"/>
    <block id="524" name="storeShelving01Top" count="23"/>
    <block id="525" name="storeShelving01TopDouble" count="32"/>
    <block id="28" name="terrainFiller" count="726"/>
    <block id="1089" name="tileFloor2WoodPainted2Block" count="338"/>
    <block id="578" name="treeBurntPine02" count="1"/>
    <block id="871" name="treeDeadPineLeaf" count="4"/>
    <block id="582" name="treeDeadTree02" count="1"/>
    <block id="1093" name="ventDuctBlock" count="16"/>
    <block id="930" name="ventDuctRamp" count="1"/>
    <block id="325" name="wallLight01" count="1"/>
    <block id="656" name="window02" count="2"/>
    <block id="1196" name="window02Broken01CTRPlate" count="4"/>
    <block id="1197" name="window02Broken02CTRPlate" count="4"/>
    <block id="1199" name="window02Broken03CTRPlate" count="2"/>
    <block id="220" name="woodBlock" count="43"/>
  </blocks>
</prefab>
